aext_share_notebook/__init__.py
aext_share_notebook-0.0.1.dist-info/METADATA
aext_share_notebook-0.0.1.dist-info/WHEEL
aext_share_notebook-0.0.1.dist-info/RECORD
